LICENSE
MANIFEST.in
README.rst
VERSION
setup.py
moth/__init__.py
moth/async_moth.py
moth/moth.py
moth.egg-info/PKG-INFO
moth.egg-info/SOURCES.txt
moth.egg-info/dependency_links.txt
moth.egg-info/requires.txt
moth.egg-info/top_level.txt