Metadata-Version: 1.1
Name: moth
Version: 2.1.1
Summary: token system using MongoDB
Home-page: https://moth.readthedocs.org
Author: Charles Thomas
Author-email: ch@rlesthom.as
License: Copyright (c) 2014 Charles Thomas
